odoo/addons/account_analytic_distribution_required/README.rst
odoo/addons/account_analytic_distribution_required/__init__.py
odoo/addons/account_analytic_distribution_required/__manifest__.py
odoo/addons/account_analytic_distribution_required/i18n/account_analytic_distribution_required.pot
odoo/addons/account_analytic_distribution_required/i18n/ar.po
odoo/addons/account_analytic_distribution_required/i18n/ca.po
odoo/addons/account_analytic_distribution_required/i18n/cs_CZ.po
odoo/addons/account_analytic_distribution_required/i18n/de.po
odoo/addons/account_analytic_distribution_required/i18n/es.po
odoo/addons/account_analytic_distribution_required/i18n/fr.po
odoo/addons/account_analytic_distribution_required/i18n/hr.po
odoo/addons/account_analytic_distribution_required/i18n/hr_HR.po
odoo/addons/account_analytic_distribution_required/i18n/pt.po
odoo/addons/account_analytic_distribution_required/i18n/pt_BR.po
odoo/addons/account_analytic_distribution_required/i18n/sl.po
odoo/addons/account_analytic_distribution_required/models/__init__.py
odoo/addons/account_analytic_distribution_required/models/account.py
odoo/addons/account_analytic_distribution_required/readme/CONFIGURE.rst
odoo/addons/account_analytic_distribution_required/readme/CONTRIBUTORS.rst
odoo/addons/account_analytic_distribution_required/readme/DESCRIPTION.rst
odoo/addons/account_analytic_distribution_required/readme/USAGE.rst
odoo/addons/account_analytic_distribution_required/static/description/icon.png
odoo/addons/account_analytic_distribution_required/static/description/index.html
odoo/addons/account_analytic_distribution_required/tests/__init__.py
odoo/addons/account_analytic_distribution_required/tests/test_account_analytic_plan_required.py
odoo12_addon_account_analytic_distribution_required-12.0.2.0.0.dist-info/METADATA
odoo12_addon_account_analytic_distribution_required-12.0.2.0.0.dist-info/WHEEL
odoo12_addon_account_analytic_distribution_required-12.0.2.0.0.dist-info/top_level.txt
odoo12_addon_account_analytic_distribution_required-12.0.2.0.0.dist-info/RECORD
