Metadata-Version: 2.1
Name: odoo12-addon-account-analytic-distribution-required
Version: 12.0.2.0.0
Summary: Account Analytic Distribution Required
Home-page: http://www.acsone.eu/
Author: ACSONE SA/NV, Tecnativa, Odoo Community Association (OCA)
Author-email: support@odoo-community.org
License: AGPL-3
Platform: UNKNOWN
Classifier: Programming Language :: Python
Classifier: Framework :: Odoo
Classifier: License :: OSI Approved :: GNU Affero General Public License v3
Requires-Python: >=3.5
Requires-Dist: odoo12-addon-account-analytic-required
Requires-Dist: odoo (<12.1dev,>=12.0a)
